bashi/__init__.py
bashi-1.1.7.dist-info/METADATA
bashi-1.1.7.dist-info/WHEEL
bashi-1.1.7.dist-info/top_level.txt
bashi-1.1.7.dist-info/RECORD
